Workbook
Name glide_00b9008d1d6a4fb08f00fb8f3ed0a5fe: Portafolio!$D$1:$D$1
Name glide_02bdecda1bc44110bb29b5943d4e6ea9: HHIReal!$AB$1:$AB$1
Name glide_03745db9d5b9469daee76b6453a3b846: Historial!$D$1:$D$1
Name glide_03af792a41e5459084b10d5e26191ab8: 'Graficos Dashboard'!$M$1:$M$1
Name glide_03dd303c81de46b4837b963ba270cc85: HHIReal!$V$1:$V$1
Name glide_0529e22de56146bd8e92d99332e37d2e: HHIReal!$M$1:$M$1
Name glide_0b1f3f60c44548448f37849b0927d3b6: Historial!$J$1:$J$1
Name glide_0dcef37f1dbd465b9870fc4bb1dc4e35: HHIReal!$N$1:$N$1
Name glide_0f103fe39a044c6f8027fa305708569a: HHIReal!$T$1:$T$1
Name glide_0f3bb8200dd54567a43ff2ddaa3edc4e: Portafolio!$N$1:$N$1
Name glide_136f0db2dc114f8e9421af329aaa6af5: HHIReal!$K$1:$K$1
Name glide_142a26aca42a44aba2e0be3f9d0e3454: 'Base de Datos'!$B$1:$B$1
Name glide_17b389b334c841d9825a938c520714ce: '🏠 Inicio'!$N$4:$N$4
Name glide_1a163bc9f7274a0aba38cd34512c59c9: Historial!$H$1:$H$1
Name glide_1a1880b3c49744dab34f2feb7b4546ea: HHIReal!$W$1:$W$1
Name glide_1c48590757bd40428c52ab15a10ea314: 'Base de Datos'!$X$1:$X$1
Name glide_1e6f6b567dab4b05886445942e8bc020: HHIReal!$J$1:$J$1
Name glide_21f004beff2345f6a6cdc5e4abd7fc3d: Portafolio!$L$1:$L$1
Name glide_279bce3f90024551a53cc84863ca9b2f: HHIReal!$L$1:$L$1
Name glide_2b663f0ca5fd45b3bdf0c248e89807d1: 'Base de Datos'!$H$1:$H$1
Name glide_2d80e0f866a4456e9ed39c3fc3d0724c: HHIReal!$P$1:$P$1
Name glide_31289df1aff54e39b3efbd0a7ae0cd8c: HHIReal!$D$1:$D$1
Name glide_36346f2ae6c4416e95586abd7de31602: 'Graficos Dashboard'!$J$1:$J$1
Name glide_36d56d6f538a44599c65bfa6d1893eb6: Portafolio!$M$1:$M$1
Name glide_370c6d8af01a4bf4b08d22ee380f081f: '🏠 Inicio'!$G$1:$G$1
Name glide_37b34dd6eaaa4e2d992ae90223aee6d4: Dashboard!$N$1:$N$1
Name glide_382daa53b6944eb6a3c9e22f1456a5a7: '🏠 Inicio'!$B$1:$B$1
Name glide_38348d16d5f14f9396f73dc13de00ac4: Dashboard!$K$1:$K$1
Name glide_384bc553e6a8433eb88f7a1c0654b896: 'Graficos Dashboard'!$F$1:$F$1
Name glide_38b2c909574a459a97039b08383d59ae: HHIReal!$G$1:$G$1
Name glide_3a1ae7a260d84942952fb0a21611e47a: Portafolio!$K$1:$K$1
Name glide_3a28c9b3045b42b89144a278b631363c: 'Base de Datos'!$O$1:$O$1
Name glide_3dfc6e0b4f29466688e03fe8d018865c: 'Base de Datos'!$D$1:$D$1
Name glide_3e14c0e826784b9db9e06f71993de942: '🏠 Inicio'!$N$4:$N$4
Name glide_3fc1fb93f0ab4fcdb24cea446f2fb020: Historial!$K$1:$K$1
Name glide_468148c8647c485ca30a7e9ffc29d6ca: Portafolio!$P$1:$P$1
Name glide_4c564737653d428d80b3a13e09153a3c: Dashboard!$S$1:$S$1
Name glide_4e1adca4e3f94768961c858b07ee30d7: Portafolio!$J$1:$J$1
Name glide_506c839151364b2797af6ed9e202dc27: Portafolio!$F$1:$F$1
Name glide_55124b9244f6452d81ed33c9cbc3286e: '🏠 Inicio'!$K$1:$K$1
Name glide_578521ddf58843099ed4a20ff822111d: HHIReal!$F$1:$F$1
Name glide_57d3329ed8e04c8082dd863bd3b95c79: HHIReal!$S$1:$S$1
Name glide_5900d1f464944b0cb092e9096baa275a: 'Graficos Dashboard'!$K$1:$K$1
Name glide_5907b4e0c2014f4ebab0585e74eb7298: 'Graficos Dashboard'!$G$1:$G$1
Name glide_59ba3abd62d5493d93390dfa543f6b58: 'Graficos Dashboard'!$D$1:$D$1
Name glide_5abd9434d47e49ca9be180b513453843: Historial!$A$1:$A$1
Name glide_5f55ae7b0efa478ea46df8d763a809c3: Historial!$F$1:$F$1
Name glide_649b66d594624ed3ba02a8f2c3a20c72: '🏠 Inicio'!$I$1:$I$1
Name glide_656bed9fac894c3985450391793ffa84: Dashboard!$A$1:$A$1
Name glide_685fcd1678c54bf5986f7fdd23ed24a7: 'Base de Datos'!$A$1:$A$1
Name glide_6bbab217809e4e4b96c23530eab28b8a: '🏠 Inicio'!$A$1:$A$1
Name glide_6ce04cd261c5413aa1abf0d2af28ca38: Dashboard!$O$1:$O$1
Name glide_6d8ee19ca732401a94534d3472a93c58: Historial!$K$1:$K$1
Name glide_6dc1f2a27e8f4f3c9cf6793a9a5ff036: HHIReal!$A$1:$A$1
Name glide_6e2159048e7544eba59eef80e958a2aa: 'Base de Datos'!$F$1:$F$1
Name glide_6e97421924564292ac6b6b30f3276748: HHIReal!$I$1:$I$1
Name glide_6ed9895e784e42cb9e71532ac523b8a2: Portafolio!$A$1:$A$1
Name glide_6ef9b66348ba4b6fa58d35839f1dc485: Historial!$C$1:$C$1
Name glide_73469a1bec0242f28c6c97c226fed98d: '🏠 Inicio'!$D$1:$D$1
Name glide_752702ba13734190b2bc76894007f60d: Dashboard!$T$1:$T$1

Sheet 🏠 Inicio
B1: 📊 Mi App de Portafolio
B2: Tu centro de control de inversiones · Toca un botón para navegar
B4: 🧭 MENÚ DE NAVEGACIÓN | F4: 💰 COMPOSICIÓN DEL PORTAFOLIO | N4: 🔒 Row ID
B13: 📊 RESUMEN EN VIVO | N13: k7RnF8aIQECi5roBy1Q3Bw
B14: 💰 Valor del Portafolio | C14: =Portafolio!E9 -> 555.31734 | N14: ZQ1qW9OCSoaoqT6VmX9GGg
B15: 💵 Total Invertido | C15: =Portafolio!F9 -> 510.67945 | N15: eYJe97t-TvihFQcQRaFW2w
B16: 📈 Ganancia Total | C16: =Portafolio!G9 -> 44.637891 | N16: QJm4T.PfQr6BE9gFQBKAAA
B17: 📊 Rendimiento % | C17: =Portafolio!H9 -> 0.087408827 | N17: K3clDgB9T1GpN4w2914AXw

Sheet Portafolio
A1: 🏠 Inicio | B1: 📈 Portafolio | C1: 📊 Dashboard | D1: 📉 Historial | E1: 🗃️ Base de Datos | F1: 📊 Gráficos | G1: 🧩 HHI Real
A3: 📈 Mi Portafolio de Inversión
A5: Acción | B5: Precio medio compra | C5: Precio actual | D5: Cantidad | E5: Valor mercado | F5: Invertido | G5: Ganancia total | H5: Rendimiento % | I5: Peso Objetivo | J5: Peso actual | K5: Desviación | L5: Cambio (%) | N5: Activo | O5: Peso Actual | P5: Peso Objetivo
A6: SPYM | B6: {=SUM((Tbla_Registros[Ticker]=A6)*(Tbla_Registros[Cantidad])*(Tbla_Registros[Precio])) / SUMIF(Tbla_Registros[Ticker], A6, Tbla_Registros[Cantidad])} -> 81.160145 | C6: =VLOOKUP(A6,'Base de Datos'!$P$4:$Q$10,2,FALSE) -> 89.11 | D6: =SUMIF(Tbla_Registros[Ticker], A6, Tbla_Registros[Cantidad]) -> 2.5024163 | E6: =C6*D6 -> 222.99032 | F6: =B6 * SUMIF(Tbla_Registros[Ticker], A6, Tbla_Registros[Cantidad]) -> 203.09647 | G6: =E6-F6 -> 19.893847 | H6: =G6/F6 -> 0.097952695 | I6: 0.4 | J6: =E6/SUM($E$6:$E$8) -> 0.40155475 | K6: =J6-I6 -> 0.0015547534 | L6: ='Base de Datos'!R5 -> 0.003378 | N6: =A6 -> SPYM | O6: =J6 -> 0.40155475 | P6: =I6 -> 0.4
A7: SCHD | B7: {=SUM((Tbla_Registros[Ticker]=A7)*(Tbla_Registros[Cantidad])*(Tbla_Registros[Precio])) / SUMIF(Tbla_Registros[Ticker], A7, Tbla_Registros[Cantidad])} -> 31.06367 | C7: =VLOOKUP(A7,'Base de Datos'!$P$4:$Q$10,2,FALSE) -> 32.59 | D7: =SUMIF(Tbla_Registros[Ticker], A7, Tbla_Registros[Cantidad]) -> 5.1141754 | E7: =C7*D7 -> 166.67098 | F7: =B7 * SUMIF(Tbla_Registros[Ticker], A7, Tbla_Registros[Cantidad]) -> 158.86506 | G7: =E7-F7 -> 7.8059195 | H7: =G7/F7 -> 0.049135535 | I7: 0.3 | J7: =E7/SUM($E$6:$E$8) -> 0.30013645 | K7: =J7-I7 -> 0.00013645278 | L7: ='Base de Datos'!R6 -> 0.006796 | N7: =A7 -> SCHD | O7: =J7 -> 0.30013645 | P7: =I7 -> 0.3
A8: SCHG | B8: {=SUM((Tbla_Registros[Ticker]=A8)*(Tbla_Registros[Cantidad])*(Tbla_Registros[Precio])) / SUMIF(Tbla_Registros[Ticker], A8, Tbla_Registros[Cantidad])} -> 31.232766 | C8: =VLOOKUP(A8,'Base de Datos'!$P$4:$Q$10,2,FALSE) -> 34.79 | D8: =SUMIF(Tbla_Registros[Ticker], A8, Tbla_Registros[Cantidad]) -> 4.7615995 | E8: =C8*D8 -> 165.65605 | F8: =B8 * SUMIF(Tbla_Registros[Ticker], A8, Tbla_Registros[Cantidad]) -> 148.71792 | G8: =E8-F8 -> 16.938125 | H8: =G8/F8 -> 0.11389431 | I8: 0.3 | J8: =E8/SUM($E$6:$E$8) -> 0.29830879 | K8: =J8-I8 -> -0.0016912062 | L8: ='Base de Datos'!R7 -> 0.003461 | N8: =A8 -> SCHG | O8: =J8 -> 0.29830879 | P8: =I8 -> 0.3
A9: Total | E9: =SUM(E6:E8) -> 555.31734 | F9: =SUBTOTAL(109,tblPortafolio[Invertido]) -> 510.67945 | G9: =SUM(G6:G8) -> 44.637891 | H9: =G9/F9 -> 0.087408827 | I9: =I6+I7+I8 -> 1
A11: 📊 Indicadores Avanzados
A12: Indicador | B12: Valor | C12: Estado
A13: Índice de Concentración (HHI) | B13: {=SUMPRODUCT(J6:J8^2)*10000} -> 3403.1625 | C13: =IF(B13<1500,"✅ Diversificado",IF(B13<2500,"🟡 Moderado","🔴 Concentrado")) -> 🔴 Concentrado
A14: Índice de Concentración (HHI) Real | B14: =HHIReal!N4 -> 184.65694 | C14: =IF(B14<1500,"✅ Diversificado",IF(B14<2500,"🟡 Moderado","🔴 Concentrado")) -> ✅ Diversificado
A15: Mayor Desviación del Objetivo | B15: {=MAX(ABS(K6:K8))} -> 0.0016912062 | C15: =IF(B15<0.02,"✅ Alineado",IF(B15<0.05,"🟡 Revisar","🔴 Rebalancear")) -> ✅ Alineado
A16: Activo con Mayor Peso | B16: =INDEX(A6:A8,MATCH(MAX(J6:J8),J6:J8,0)) -> SPYM | C16: =MAX(J6:J8) -> 0.40155475
A17: Ganancia Promedio por Activo | B17: =AVERAGE(G6:G8) -> 14.879297 | C17: =IF(B17>0,"✅ Positivo","🔴 Negativo") -> ✅ Positivo
A18: Días Invertido | B18: =TODAY()-MIN(Tbla_Registros[Fecha]) -> 58 | C18: 📅 Desde primera compra
A19: Rendimiento Anualizado | B19: =IF(B18>0,((1+H9)^(365/B18))-1,0) -> 0.69443141 | C19: 📈 Proyección a 1 año
A20: Spread de Rendimiento | B20: =MAX(H6:H8)-MIN(H6:H8) -> 0.064758777 | C20: 📊 Dispersión entre activos
A21: Alpha vs S&P 500 | B21: =Dashboard!B21 -> -0.020792646 | C21: =IF(B21>0.01,"✅ Superando benchmark",IF(B21<-0.01,"⚠️ Por debajo del benchmark","🎯 En línea con benchmark")) -> ⚠️ Por debajo del benchmark
A22: Rendimiento por Día Promedio | B22: =IF(B18>0,G9/B18,0) -> 0.76961882 | C22: 💵 Ganancia diaria promedio
A23: Mejor Compra | B23: =_xlfn.XLOOKUP(MAX(Tbla_Registros[Rendimiento %]),Tbla_Registros[Rendimiento %],Tbla_Registros[Ticker],"") -> SCHG | C23: ="🏆 Mayor rendimiento: "&TEXT(MAX(Tbla_Registros[Rendimiento %]),"0.00%") -> 🏆 Mayor rendimiento: 19.59%
A24: Próximo Hito ($600) | B24: =IF(E9>=600,"✅ Alcanzado","Faltan: "&TEXT(MAX(0,600-E9),"$#,##0.00")) -> Faltan: $44.68 | C24: =IF(E9>=600,"🎯 100% completado","🎯 "&TEXT(MIN(E9/600,1),"0.00%")&" completado") -> 🎯 92.55% completado
A26: 💰 Composición del Portafolio
A27: Concepto | B27: Monto | C27: % del Total
A28: 💵 Aportaciones | B28: =F9 -> 510.67945 | C28: =F9/E9 -> 0.91961733
A29: 📈 Ganancia | B29: =G9 -> 44.637891 | C29: =G9/E9 -> 0.080382672
A30: Total | B30: =E9 -> 555.31734 | C30: 1
A33: 🚦 Alertas Accionables
A34: Activo | B34: Desviación | C34: Acción Recomendada
A35: =A6 -> SPYM | B35: =K6 -> 0.0015547534 | C35: =IF(ABS(K6)<=0.01,"✅ Alineado",IF(K6>0,"🔴 Reducir "&A6&" (sobre-ponderado)","🟡 Aumentar "&A6&" (sub-ponderado)")) -> ✅ Alineado
A36: =A7 -> SCHD | B36: =K7 -> 0.00013645278 | C36: =IF(ABS(K7)<=0.01,"✅ Alineado",IF(K7>0,"🔴 Reducir "&A7&" (sobre-ponderado)","🟡 Aumentar "&A7&" (sub-ponderado)")) -> ✅ Alineado
A37: =A8 -> SCHG | B37: =K8 -> -0.0016912062 | C37: =IF(ABS(K8)<=0.01,"✅ Alineado",IF(K8>0,"🔴 Reducir "&A8&" (sobre-ponderado)","🟡 Aumentar "&A8&" (sub-ponderado)")) -> ✅ Alineado
A39: =IF(MAX(ABS(K6),ABS(K7),ABS(K8))<=0.01,"✅ Portafolio Balanceado — sin acciones requeridas","⚠️ Hay activos fuera de rango — revisa las acciones recomendadas") -> ✅ Portafolio Balanceado — sin acciones requeridas

Sheet Dashboard
A1: 🏠 Inicio | B1: 📈 Portafolio | C1: 📊 Dashboard | D1: 📉 Historial | E1: 🗃️ Base de Datos | F1: 📊 Gráficos | G1: 🧩 HHI Real
A3: 📊 Indicadores Clave | D3: 🔄 Rebalanceo por Aportación | S3: 💰 Resumen de Dividendos
A4: Indicador | B4: Datos | D4: Acción | E4: Monto Ideal | F4: Monto Actual | G4: Déficit | H4: Asignación | I4: Unidades a Comprar | K4: 🕐 Última Actualización | M4: 🏆 Top 5 Holdings Reales | S4: Indicador | T4: Valor
A5: Valor total del portafolio | B5: =Portafolio!E9 -> 555.31734 | D5: SPYM | E5: =_xlfn.XLOOKUP($D5,Portafolio!$A$6:$A$8,Portafolio!$I$6:$I$8) * SUM(Portafolio!$E$6:$E$8) -> 222.12694 | F5: =_xlfn.XLOOKUP($D5,Portafolio!$A$6:$A$8,Portafolio!$E$6:$E$8) -> 222.99032 | G5: =E5-F5 -> -0.86338154 | H5: =MAX(0, _xlfn.XLOOKUP($D5,Portafolio!$A$6:$A$8,Portafolio!$I$6:$I$8) * (SUM(Portafolio!$E$6:$E$8) + $B$15) - _xlfn.XLOOKUP($D5,Portafolio!$A$6:$A$8,Portafolio!$E$6:$E$8)) -> 0 | I5: =IF($H5>0, $H5 / _xlfn.XLOOKUP($D5,Portafolio!$A$6:$A$8,Portafolio!$C$6:$C$8), 0) -> 0 | K5: =TODAY() -> 46177 | M5: Ticker | N5: Peso % | S5: 📊 Total Dividendos | T5: =SUMIF(Tbla_Registros[Tipo],"Dividendo",Tbla_Registros[Total]) -> 0
A6: Total invertido | B6: =Portafolio!F9 -> 510.67945 | D6: SCHD | E6: =_xlfn.XLOOKUP($D6,Portafolio!$A$6:$A$8,Portafolio!$I$6:$I$8) * SUM(Portafolio!$E$6:$E$8) -> 166.5952 | F6: =_xlfn.XLOOKUP($D6,Portafolio!$A$6:$A$8,Portafolio!$E$6:$E$8) -> 166.67098 | G6: =E6-F6 -> -0.075774597 | H6: =MAX(0, _xlfn.XLOOKUP($D6,Portafolio!$A$6:$A$8,Portafolio!$I$6:$I$8) * (SUM(Portafolio!$E$6:$E$8) + $B$15) - _xlfn.XLOOKUP($D6,Portafolio!$A$6:$A$8,Portafolio!$E$6:$E$8)) -> 0 | I6: =IF($H6>0, $H6 / _xlfn.XLOOKUP($D6,Portafolio!$A$6:$A$8,Portafolio!$C$6:$C$8), 0) -> 0 | M6: =HHIReal!J12 -> NVDA | N6: =HHIReal!K12 -> 0.071659471 | S6: 📋 # Dividendos | T6: =COUNTIF(Tbla_Registros[Tipo],"Dividendo") -> 0
A7: Ganancia total | B7: =B5 - B6 -> 44.637891 | D7: SCHG | E7: =_xlfn.XLOOKUP($D7,Portafolio!$A$6:$A$8,Portafolio!$I$6:$I$8) * SUM(Portafolio!$E$6:$E$8) -> 166.5952 | F7: =_xlfn.XLOOKUP($D7,Portafolio!$A$6:$A$8,Portafolio!$E$6:$E$8) -> 165.65605 | G7: =E7-F7 -> 0.93915614 | H7: =MAX(0, _xlfn.XLOOKUP($D7,Portafolio!$A$6:$A$8,Portafolio!$I$6:$I$8) * (SUM(Portafolio!$E$6:$E$8) + $B$15) - _xlfn.XLOOKUP($D7,Portafolio!$A$6:$A$8,Portafolio!$E$6:$E$8)) -> 0.93915614 | I7: =IF($H7>0, $H7 / _xlfn.XLOOKUP($D7,Portafolio!$A$6:$A$8,Portafolio!$C$6:$C$8), 0) -> 0.026995003 | K7: 🎯 Próxima Meta | M7: =HHIReal!J13 -> AAPL | N7: =HHIReal!K13 -> 0.055982166 | S7: 💵 SPYM | T7: =SUMIFS(Tbla_Registros[Total],Tbla_Registros[Tipo],"Dividendo",Tbla_Registros[Ticker],"SPYM") -> 0
A8: Rendimiento % | B8: =(B5 - B6) / B6 -> 0.087408827 | K8: Meta: | L8: 1000 | M8: =HHIReal!J14 -> MSFT | N8: =HHIReal!K14 -> 0.038632401 | S8: 💵 SCHD | T8: =SUMIFS(Tbla_Registros[Total],Tbla_Registros[Tipo],"Dividendo",Tbla_Registros[Ticker],"SCHD") -> 0
A9: Mejor activo | B9: =INDEX(Portafolio!A6:A8, MATCH(MAX(Portafolio!H6:H8), Portafolio!H6:H8, 0)) -> SCHG | D9: 📝 La asignación prioriza activos sub-ponderados (déficit positivo) para rebalancear | K9: Faltan: | L9: =MAX(0,L8-B5) -> 444.68266 | M9: =HHIReal!J15 -> AMZN | N9: =HHIReal!K15 -> 0.033516097 | S9: 💵 SCHG | T9: =SUMIFS(Tbla_Registros[Total],Tbla_Registros[Tipo],"Dividendo",Tbla_Registros[Ticker],"SCHG") -> 0
A10: Peor activo | B10: =INDEX(Portafolio!A6:A8, MATCH(MIN(Portafolio!H6:H8), Portafolio!H6:H8, 0)) -> SCHD | D10: ⚠️ Alerta Rebalanceo: | E10: {=IF(MAX(ABS(Portafolio!K6:K8))>0.05,"🔴 REBALANCEO NECESARIO - Desviación > 5%","✅ Portafolio Balanceado")} -> ✅ Portafolio Balanceado | K10: Progreso: | L10: =MIN(B5/L8,1) -> 0.55531734 | M10: =HHIReal!J16 -> GOOGL | N10: =HHIReal!K16 -> 0.029881178 | S10: 📈 Promedio/Div | T10: =IFERROR(AVERAGEIF(Tbla_Registros[Tipo],"Dividendo",Tbla_Registros[Total]),0) -> 0
A11: Activo mas Grande | B11: =INDEX(Portafolio!A6:A8, MATCH(MAX(Portafolio!J6:J8), Portafolio!J6:J8, 0)) -> SPYM | K11: 📅 Proyección de Meta
A12: Peso Activo mas Grande | B12: =MAX(Portafolio!J6:J8) -> 0.40155475 | D12: 📊 Distribución: Actual vs Objetivo | K12: Ganancia/Día: | L12: =IF(Portafolio!B18>0,Portafolio!G9/Portafolio!B18,0) -> 0.76961882 | M12: 📊 Nivel Diversificación | S12: 📈 Yield Estimado | T12: Anual
D13: Activo | E13: Peso Actual | F13: Peso Objetivo | K13: Días para Meta: | L13: =IF(L12>0,ROUND((L8-B5)/L12,0),"N/A") -> 578 | M13: HHI Real: | N13: =HHIReal!N4 -> 184.65694 | S13: Yield Anual: | T13: =Portafolio!E6*0.013+Portafolio!E7*0.035+Portafolio!E8*0.003 -> 9.2293264
A14: 🔄APORTACION | D14: SPYM | E14: =Portafolio!J6 -> 0.40155475 | F14: =Portafolio!I6 -> 0.4 | K14: Fecha Estimada: | L14: =IF(ISNUMBER(L13),TODAY()+L13,"N/A") -> 46755 | M14: Estado: | N14: =HHIReal!N5 -> ✅ Muy Diversificado | S14: Yield %: | T14: =IF(B5>0,T13/B5,0) -> 0.016619914
A15: Apotacion del Periodo | B15: 0 | D15: SCHD | E15: =Portafolio!J7 -> 0.30013645 | F15: =Portafolio!I7 -> 0.3 | K15: Compras: | L15: =COUNTIFS(Tbla_Registros[Fecha],">="&DATE(YEAR(TODAY()),MONTH(TODAY()),1),Tbla_Registros[Tipo],"Compra") -> 3
D16: SCHG | E16: =Portafolio!J8 -> 0.29830879 | F16: =Portafolio!I8 -> 0.3 | M16: 📱 Inversión por App
M17: App | N17: Total
A18: Rendimiento del S&P 500 YTD | B18: YTD% | M18: Fintual | N18: =SUMIF('Base de Datos'!M:M,"Fintual",'Base de Datos'!I:I) -> 453.50765
A19: S&P500 | B19: ='Base de Datos'!T8 -> 0.10820147 | M19: Webull | N19: =SUMIF('Base de Datos'!M:M,"Webull",'Base de Datos'!I:I) -> 57.171804
A20: Portafolio | B20: =B8 -> 0.087408827
A21: Diferencia vs Benchmark | B21: =B20-B19 -> -0.020792646
P22: Concepto | Q22: Monto
A23: 📝 Notas de | B23: Inversión | P23: Actual | Q23: =Portafolio!E9 -> 555.31734
A24: Fecha | B24: Nota/Comentario | P24: Meta | Q24: =L8 -> 1000
A25: =TODAY() -> 46177 | B25: Libro de portafolio completado

Sheet Graficos Dashboard
A1: 🏠 Inicio | B1: 📈 Portafolio | C1: 📊 Dashboard | D1: 📉 Historial | E1: 🗃️ Base de Datos | F1: 📊 Gráficos | G1: 🧩 HHI Real
A3: 📊 Gráficos del Dashboard
A4: Visualizaciones actualizadas automáticamente
A40: 📝 Los gráficos se actualizan automáticamente con los datos del Dashboard, Portafolio y Base de Datos
A41: 🕐 Última actualización: | B41: =TODAY() -> 46177

Sheet Base de Datos
A1: 🏠 Inicio | B1: 📈 Portafolio | C1: 📊 Dashboard | D1: 📉 Historial | E1: 🗃️ Base de Datos | F1: 📊 Gráficos | G1: 🧩 HHI Real | Z1: 🔒 Row ID
A3: 📒Registro de Operaciones | P3: 📊 Tabla de Precios | Z3: jd20HlbKRIKH3P39exdU2g
P4: Ticker | Q4: Precio Actual | R4: Cambio (%) | S4: Precio Inicio Año | T4: YTD% | U4: 5Y% | V4: 10Y% | W4: Cotización | Z4: qeFzIQLzTgycZpX.942BMw
A5: ID | B5: Fecha | C5: Ticker | D5: Activo | E5: Tipo | F5: Cantidad | G5: Precio | H5: Comisión | I5: Total | J5: Rendimiento % | K5: Días | L5: Ganancia | M5: App | P5: SPYM | Q5: {=_FV(W5,"Precio")} -> 89.11 | R5: {=_FV(W5,"Cambio (%)",TRUE)} -> 0.003378 | S5: 80.39 | T5: =(Q5-S5)/S5 -> 0.1084712 | U5: =(Q5-X5)/X5 -> 0.82154538 | V5: =(Q5-Y5)/Y5 -> 2.6898551 | W5: #VALUE! | X5: 48.92 | Y5: 24.15 | Z5: jSEYqfThSumZeTcuGxLOyw
A6: =ROW()-ROW($A$6)+1 -> 1 | B6: 46119 | C6: SPYM | D6: =IF(Tbla_Registros[[#This Row],[Ticker]]="","",_xlfn.XLOOKUP(Tbla_Registros[[#This Row],[Ticker]],$P$14:$P$19,$Q$14:$Q$19,Tbla_Registros[[#This Row],[Ticker]])) -> SPDR S&P 500 | E6: Compra | F6: 1.1686298 | G6: 76.75 | H6: 0 | I6: =Tbla_Registros[[#This Row],[Cantidad]] * Tbla_Registros[[#This Row],[Precio]] + Tbla_Registros[[#This Row],[Comisión]] -> 89.692337 | J6: =IF(C6="","",IFERROR((VLOOKUP(C6,Portafolio!$A$6:$C$8,3,FALSE)-G6)/G6,"")) -> 0.16104235 | K6: =IF(B6="","",TODAY()-B6) -> 58 | L6: =IFERROR((VLOOKUP(C6,Portafolio!$A$6:$C$8,3,FALSE)-G6)*F6,"") -> 14.444264 | M6: Fintual | P6: SCHD | Q6: {=_FV(W6,"Precio")} -> 32.59 | R6: {=_FV(W6,"Cambio (%)",TRUE)} -> 0.006796 | S6: 27.73 | T6: =(Q6-S6)/S6 -> 0.17526145 | U6: =(Q6-X6)/X6 -> 0.27304688 | V6: =(Q6-Y6)/Y6 -> 1.4559156 | W6: #VALUE! | X6: 25.6 | Y6: 13.27 | Z6: fku2cKeJRHqZmjsa9WZ0Wg
A7: =ROW()-ROW($A$6)+1 -> 2 | B7: 46119 | C7: SCHD | D7: =IF(Tbla_Registros[[#This Row],[Ticker]]="","",_xlfn.XLOOKUP(Tbla_Registros[[#This Row],[Ticker]],$P$14:$P$19,$Q$14:$Q$19,Tbla_Registros[[#This Row],[Ticker]])) -> Schwab Dividend | E7: Compra | F7: 1 | G7: 30.59 | H7: 0 | I7: =Tbla_Registros[[#This Row],[Cantidad]] * Tbla_Registros[[#This Row],[Precio]] + Tbla_Registros[[#This Row],[Comisión]] -> 30.59 | J7: =IF(C7="","",IFERROR((VLOOKUP(C7,Portafolio!$A$6:$C$8,3,FALSE)-G7)/G7,"")) -> 0.065380843 | K7: =IF(B7="","",TODAY()-B7) -> 58 | L7: =IFERROR((VLOOKUP(C7,Portafolio!$A$6:$C$8,3,FALSE)-G7)*F7,"") -> 2 | M7: Fintual | P7: SCHG | Q7: {=_FV(W7,"Precio")} -> 34.79 | R7: {=_FV(W7,"Cambio (%)",TRUE)} -> 0.003461 | S7: 32.5 | T7: =(Q7-S7)/S7 -> 0.070461538 | U7: =(Q7-X7)/X7 -> 1.067142 | V7: =(Q7-Y7)/Y7 -> 4.3523077 | W7: #VALUE! | X7: 16.83 | Y7: 6.5 | Z7: XSPbOUleTWuJXfUjs81kpA
A8: =ROW()-ROW($A$6)+1 -> 3 | B8: 46119 | C8: SCHD | D8: =IF(Tbla_Registros[[#This Row],[Ticker]]="","",_xlfn.XLOOKUP(Tbla_Registros[[#This Row],[Ticker]],$P$14:$P$19,$Q$14:$Q$19,Tbla_Registros[[#This Row],[Ticker]])) -> Schwab Dividend | E8: Compra | F8: 1.1981079 | G8: 30.59 | H8: 0 | I8: =Tbla_Registros[[#This Row],[Cantidad]] * Tbla_Registros[[#This Row],[Precio]] + Tbla_Registros[[#This Row],[Comisión]] -> 36.65012 | J8: =IF(C8="","",IFERROR((VLOOKUP(C8,Portafolio!$A$6:$C$8,3,FALSE)-G8)/G8,"")) -> 0.065380843 | K8: =IF(B8="","",TODAY()-B8) -> 58 | L8: =IFERROR((VLOOKUP(C8,Portafolio!$A$6:$C$8,3,FALSE)-G8)*F8,"") -> 2.3962157 | M8: Fintual | P8: SPY | Q8: {=_FV(W8,"Precio")} -> 757.09 | R8: {=_FV(W8,"Cambio (%)",TRUE)} -> 0.003779 | S8: 683.17 | T8: =(Q8-S8)/S8 -> 0.10820147 | U8: =(Q8-X8)/X8 -> 0.82457705 | V8: =(Q8-Y8)/Y8 -> 2.6843155 | W8: #VALUE! | X8: 414.94 | Y8: 205.49 | Z8: P2tmliSBQWiRkeLZBAQA8Q
A9: =ROW()-ROW($A$6)+1 -> 4 | B9: 46119 | C9: SCHG | D9: =IF(Tbla_Registros[[#This Row],[Ticker]]="","",_xlfn.XLOOKUP(Tbla_Registros[[#This Row],[Ticker]],$P$14:$P$19,$Q$14:$Q$19,Tbla_Registros[[#This Row],[Ticker]])) -> Schwab Growth | E9: Compra | F9: 1 | G9: 29.09 | H9: 0 | I9: =Tbla_Registros[[#This Row],[Cantidad]] * Tbla_Registros[[#This Row],[Precio]] + Tbla_Registros[[#This Row],[Comisión]] -> 29.09 | J9: =IF(C9="","",IFERROR((VLOOKUP(C9,Portafolio!$A$6:$C$8,3,FALSE)-G9)/G9,"")) -> 0.19594362 | K9: =IF(B9="","",TODAY()-B9) -> 58 | L9: =IFERROR((VLOOKUP(C9,Portafolio!$A$6:$C$8,3,FALSE)-G9)*F9,"") -> 5.7 | M9: Fintual | P9: QQQ | Q9: {=_FV(W9,"Precio")} -> 740.61 | R9: {=_FV(W9,"Cambio (%)",TRUE)} -> -0.004837 | S9: 613.12 | T9: =(Q9-S9)/S9 -> 0.20793646 | U9: =(Q9-X9)/X9 -> 1.2647931 | V9: =(Q9-Y9)/Y9 -> 5.956044 | W9: #VALUE! | X9: 327.01 | Y9: 106.47 | Z9: 22JfD1ENTu2dg.-sw9konw
A10: =ROW()-ROW($A$6)+1 -> 5 | B10: 46119 | C10: SCHG | D10: =IF(Tbla_Registros[[#This Row],[Ticker]]="","",_xlfn.XLOOKUP(Tbla_Registros[[#This Row],[Ticker]],$P$14:$P$19,$Q$14:$Q$19,Tbla_Registros[[#This Row],[Ticker]])) -> Schwab Growth | E10: Compra | F10: 1.3133105 | G10: 29.09 | H10: 0 | I10: =Tbla_Registros[[#This Row],[Cantidad]] * Tbla_Registros[[#This Row],[Precio]] + Tbla_Registros[[#This Row],[Comisión]] -> 38.204203 | J10: =IF(C10="","",IFERROR((VLOOKUP(C10,Portafolio!$A$6:$C$8,3,FALSE)-G10)/G10,"")) -> 0.19594362 | K10: =IF(B10="","",TODAY()-B10) -> 58 | L10: =IFERROR((VLOOKUP(C10,Portafolio!$A$6:$C$8,3,FALSE)-G10)*F10,"") -> 7.4858699 | M10: Fintual | P10: BND | Q10: {=_FV(W10,"Precio")} -> 73.16 | R10: {=_FV(W10,"Cambio (%)",TRUE)} -> 0.001369 | S10: 74.04 | T10: =(Q10-S10)/S10 -> -0.011885467 | U10: =(Q10-X10)/X10 -> -0.14030552 | V10: =(Q10-Y10)/Y10 -> -0.12383234 | W10: #VALUE! | X10: 85.1 | Y10: 83.5 | Z10: RqGujMSTTJmszJ8UhTvHhg
A11: =ROW()-ROW($A$6)+1 -> 6 | B11: 46127 | C11: SCHD | D11: =IF(Tbla_Registros[[#This Row],[Ticker]]="","",_xlfn.XLOOKUP(Tbla_Registros[[#This Row],[Ticker]],$P$14:$P$19,$Q$14:$Q$19,Tbla_Registros[[#This Row],[Ticker]])) -> Schwab Dividend | E11: Compra | F11: 0.68844123 | G11: 30.68 | H11: 0 | I11: =Tbla_Registros[[#This Row],[Cantidad]] * Tbla_Registros[[#This Row],[Precio]] + Tbla_Registros[[#This Row],[Comisión]] -> 21.121377 | J11: =IF(C11="","",IFERROR((VLOOKUP(C11,Portafolio!$A$6:$C$8,3,FALSE)-G11)/G11,"")) -> 0.062255541 | K11: =IF(B11="","",TODAY()-B11) -> 50 | L11: =IFERROR((VLOOKUP(C11,Portafolio!$A$6:$C$8,3,FALSE)-G11)*F11,"") -> 1.3149227 | M11: Fintual | Z11: imNhMiCGRa6yvazJ.MYRTg
A12: =ROW()-ROW($A$6)+1 -> 7 | B12: 46127 | C12: SCHG | D12: =IF(Tbla_Registros[[#This Row],[Ticker]]="","",_xlfn.XLOOKUP(Tbla_Registros[[#This Row],[Ticker]],$P$14:$P$19,$Q$14:$Q$19,Tbla_Registros[[#This Row],[Ticker]])) -> Schwab Growth | E12: Compra | F12: 0.45307039 | G12: 32.05 | H12: 0 | I12: =Tbla_Registros[[#This Row],[Cantidad]] * Tbla_Registros[[#This Row],[Precio]] + Tbla_Registros[[#This Row],[Comisión]] -> 14.520906 | J12: =IF(C12="","",IFERROR((VLOOKUP(C12,Portafolio!$A$6:$C$8,3,FALSE)-G12)/G12,"")) -> 0.08549142 | K12: =IF(B12="","",TODAY()-B12) -> 50 | L12: =IFERROR((VLOOKUP(C12,Portafolio!$A$6:$C$8,3,FALSE)-G12)*F12,"") -> 1.2414129 | M12: Fintual | Z12: a-uT0KHm6SAeoULTj-tbD5w
A13: =ROW()-ROW($A$6)+1 -> 8 | B13: 46127 | C13: SPYM | D13: =IF(Tbla_Registros[[#This Row],[Ticker]]="","",_xlfn.XLOOKUP(Tbla_Registros[[#This Row],[Ticker]],$P$14:$P$19,$Q$14:$Q$19,Tbla_Registros[[#This Row],[Ticker]])) -> SPDR S&P 500 | E13: Compra | F13: 0.26735368 | G13: 82.29 | H13: 0 | I13: =Tbla_Registros[[#This Row],[Cantidad]] * Tbla_Registros[[#This Row],[Precio]] + Tbla_Registros[[#This Row],[Comisión]] -> 22.000535 | J13: =IF(C13="","",IFERROR((VLOOKUP(C13,Portafolio!$A$6:$C$8,3,FALSE)-G13)/G13,"")) -> 0.082877628 | K13: =IF(B13="","",TODAY()-B13) -> 50 | L13: =IFERROR((VLOOKUP(C13,Portafolio!$A$6:$C$8,3,FALSE)-G13)*F13,"") -> 1.8233521 | M13: Fintual | P13: Ticker | Q13: Nombre Activo | Z13: nannz3yJShez6QbeBliDFQ
A14: =ROW()-ROW($A$6)+1 -> 9 | B14: 46128 | C14: SCHD | D14: =IF(Tbla_Registros[[#This Row],[Ticker]]="","",_xlfn.XLOOKUP(Tbla_Registros[[#This Row],[Ticker]],$P$14:$P$19,$Q$14:$Q$19,Tbla_Registros[[#This Row],[Ticker]])) -> Schwab Dividend | E14: Compra | F14: 0.56204948 | G14: 30.8 | H14: 0 | I14: =Tbla_Registros[[#This Row],[Cantidad]] * Tbla_Registros[[#This Row],[Precio]] + Tbla_Registros[[#This Row],[Comisión]] -> 17.311124 | J14: =IF(C14="","",IFERROR((VLOOKUP(C14,Portafolio!$A$6:$C$8,3,FALSE)-G14)/G14,"")) -> 0.058116883 | K14: =IF(B14="","",TODAY()-B14) -> 49 | L14: =IFERROR((VLOOKUP(C14,Portafolio!$A$6:$C$8,3,FALSE)-G14)*F14,"") -> 1.0060686 | M14: Fintual | P14: SPYM | Q14: SPDR S&P 500 | Z14: BYruPCqQQO6FI463OZsHEg
A15: =ROW()-ROW($A$6)+1 -> 10 | B15: 46128 | C15: SCHG | D15: =IF(Tbla_Registros[[#This Row],[Ticker]]="","",_xlfn.XLOOKUP(Tbla_Registros[[#This Row],[Ticker]],$P$14:$P$19,$Q$14:$Q$19,Tbla_Registros[[#This Row],[Ticker]])) -> Schwab Growth | E15: Compra | F15: 0.53610299 | G15: 32.16 | H15: 0 | I15: =Tbla_Registros[[#This Row],[Cantidad]] * Tbla_Registros[[#This Row],[Precio]] + Tbla_Registros[[#This Row],[Comisión]] -> 17.241072 | J15: =IF(C15="","",IFERROR((VLOOKUP(C15,Portafolio!$A$6:$C$8,3,FALSE)-G15)/G15,"")) -> 0.081778607 | K15: =IF(B15="","",TODAY()-B15) -> 49 | L15: =IFERROR((VLOOKUP(C15,Portafolio!$A$6:$C$8,3,FALSE)-G15)*F15,"") -> 1.4099509 | M15: Fintual | P15: SCHD | Q15: Schwab Dividend | Z15: oGZ0B4eXSkuEu0dyOBZ0aA
A16: =ROW()-ROW($A$6)+1 -> 11 | B16: 46128 | C16: SPYM | D16: =IF(Tbla_Registros[[#This Row],[Ticker]]="","",_xlfn.XLOOKUP(Tbla_Registros[[#This Row],[Ticker]],$P$14:$P$19,$Q$14:$Q$19,Tbla_Registros[[#This Row],[Ticker]])) -> SPDR S&P 500 | E16: Compra | F16: 0.27869924 | G16: 82.6 | H16: 0 | I16: =Tbla_Registros[[#This Row],[Cantidad]] * Tbla_Registros[[#This Row],[Precio]] + Tbla_Registros[[#This Row],[Comisión]] -> 23.020557 | J16: =IF(C16="","",IFERROR((VLOOKUP(C16,Portafolio!$A$6:$C$8,3,FALSE)-G16)/G16,"")) -> 0.078813559 | K16: =IF(B16="","",TODAY()-B16) -> 49 | L16: =IFERROR((VLOOKUP(C16,Portafolio!$A$6:$C$8,3,FALSE)-G16)*F16,"") -> 1.8143321 | M16: Fintual | P16: SCHG | Q16: Schwab Growth | Z16: a-T3L42boSx-CXLVR11bP9w
A17: =ROW()-ROW($A$6)+1 -> 12 | B17: 46142 | C17: SCHD | D17: =IF(Tbla_Registros[[#This Row],[Ticker]]="","",_xlfn.XLOOKUP(Tbla_Registros[[#This Row],[Ticker]],$P$14:$P$19,$Q$14:$Q$19,Tbla_Registros[[#This Row],[Ticker]])) -> Schwab Dividend | E17: Compra | F17: 0.48502095 | G17: 31.98 | H17: 0 | I17: =Tbla_Registros[[#This Row],[Cantidad]] * Tbla_Registros[[#This Row],[Precio]] + Tbla_Registros[[#This Row],[Comisión]] -> 15.51097 | J17: =IF(C17="","",IFERROR((VLOOKUP(C17,Portafolio!$A$6:$C$8,3,FALSE)-G17)/G17,"")) -> 0.019074422 | K17: =IF(B17="","",TODAY()-B17) -> 35 | L17: =IFERROR((VLOOKUP(C17,Portafolio!$A$6:$C$8,3,FALSE)-G17)*F17,"") -> 0.29586278 | M17: Fintual | P17: SPY | Q17: SPDR S&P 500 ETF | Z17: 1QYO18KUTUaWdCSRXg1QxA
A18: =ROW()-ROW($A$6)+1 -> 13 | B18: 46142 | C18: SCHG | D18: =IF(Tbla_Registros[[#This Row],[Ticker]]="","",_xlfn.XLOOKUP(Tbla_Registros[[#This Row],[Ticker]],$P$14:$P$19,$Q$14:$Q$19,Tbla_Registros[[#This Row],[Ticker]])) -> Schwab Growth | E18: Compra | F18: 0.54343175 | G18: 32.72 | H18: 0 | I18: =Tbla_Registros[[#This Row],[Cantidad]] * Tbla_Registros[[#This Row],[Precio]] + Tbla_Registros[[#This Row],[Comisión]] -> 17.781087 | J18: =IF(C18="","",IFERROR((VLOOKUP(C18,Portafolio!$A$6:$C$8,3,FALSE)-G18)/G18,"")) -> 0.063264059 | K18: =IF(B18="","",TODAY()-B18) -> 35 | L18: =IFERROR((VLOOKUP(C18,Portafolio!$A$6:$C$8,3,FALSE)-G18)*F18,"") -> 1.1249037 | M18: Fintual | P18: QQQ | Q18: Invesco QQQ | Z18: cnqkxisCT.6nR6Sa76XFeQ
A19: =ROW()-ROW($A$6)+1 -> 14 | B19: 46142 | C19: SPYM | D19: =IF(Tbla_Registros[[#This Row],[Ticker]]="","",_xlfn.XLOOKUP(Tbla_Registros[[#This Row],[Ticker]],$P$14:$P$19,$Q$14:$Q$19,Tbla_Registros[[#This Row],[Ticker]])) -> SPDR S&P 500 | E19: Compra | F19: 0.27833876 | G19: 84.18 | H19: 0 | I19: =Tbla_Registros[[#This Row],[Cantidad]] * Tbla_Registros[[#This Row],[Precio]] + Tbla_Registros[[#This Row],[Comisión]] -> 23.430557 | J19: =IF(C19="","",IFERROR((VLOOKUP(C19,Portafolio!$A$6:$C$8,3,FALSE)-G19)/G19,"")) -> 0.05856498 | K19: =IF(B19="","",TODAY()-B19) -> 35 | L19: =IFERROR((VLOOKUP(C19,Portafolio!$A$6:$C$8,3,FALSE)-G19)*F19,"") -> 1.3722101 | M19: Fintual | P19: BND | Q19: Vanguard Total Bond | Z19: 5EyuSRCBQ7-X72dbjDBsYg
A20: =ROW()-ROW($A$6)+1 -> 15 | B20: 46157 | C20: SCHD | D20: =IF(Tbla_Registros[[#This Row],[Ticker]]="","",_xlfn.XLOOKUP(Tbla_Registros[[#This Row],[Ticker]],$P$14:$P$19,$Q$14:$Q$19,Tbla_Registros[[#This Row],[Ticker]])) -> Schwab Dividend | E20: Compra | F20: 0.55867331 | G20: 31.72 | H20: 0 | I20: =Tbla_Registros[[#This Row],[Cantidad]] * Tbla_Registros[[#This Row],[Precio]] + Tbla_Registros[[#This Row],[Comisión]] -> 17.721117 | J20: =IF(C20="","",IFERROR((VLOOKUP(C20,Portafolio!$A$6:$C$8,3,FALSE)-G20)/G20,"")) -> 0.027427491 | K20: =IF(B20="","",TODAY()-B20) -> 20 | L20: =IFERROR((VLOOKUP(C20,Portafolio!$A$6:$C$8,3,FALSE)-G20)*F20,"") -> 0.48604578 | M20: Fintual | Z20: znBAVWnYQ--yigOZeQZtCg
A21: =ROW()-ROW($A$6)+1 -> 16 | B21: 46160 | C21: SPYM | D21: =IF(Tbla_Registros[[#This Row],[Ticker]]="","",_xlfn.XLOOKUP(Tbla_Registros[[#This Row],[Ticker]],$P$14:$P$19,$Q$14:$Q$19,Tbla_Registros[[#This Row],[Ticker]])) -> SPDR S&P 500 | E21: Compra | F21: 0.21404483 | G21: 87.18 | H21: 0 | I21: =Tbla_Registros[[#This Row],[Cantidad]] * Tbla_Registros[[#This Row],[Precio]] + Tbla_Registros[[#This Row],[Comisión]] -> 18.660428 | J21: =IF(C21="","",IFERROR((VLOOKUP(C21,Portafolio!$A$6:$C$8,3,FALSE)-G21)/G21,"")) -> 0.022138105 | K21: =IF(B21="","",TODAY()-B21) -> 17 | L21: =IFERROR((VLOOKUP(C21,Portafolio!$A$6:$C$8,3,FALSE)-G21)*F21,"") -> 0.41310652 | M21: Fintual | Z21: fbZsEjV.TUmZ5GltW946kw
A22: =ROW()-ROW($A$6)+1 -> 17 | B22: 46160 | C22: SCHG | D22: =IF(Tbla_Registros[[#This Row],[Ticker]]="","",_xlfn.XLOOKUP(Tbla_Registros[[#This Row],[Ticker]],$P$14:$P$19,$Q$14:$Q$19,Tbla_Registros[[#This Row],[Ticker]])) -> Schwab Growth | E22: Compra | F22: 0.38309384 | G22: 34.38 | H22: 0 | I22: =Tbla_Registros[[#This Row],[Cantidad]] * Tbla_Registros[[#This Row],[Precio]] + Tbla_Registros[[#This Row],[Comisión]] -> 13.170766 | J22: =IF(C22="","",IFERROR((VLOOKUP(C22,Portafolio!$A$6:$C$8,3,FALSE)-G22)/G22,"")) -> 0.011925538 | K22: =IF(B22="","",TODAY()-B22) -> 17 | L22: =IFERROR((VLOOKUP(C22,Portafolio!$A$6:$C$8,3,FALSE)-G22)*F22,"") -> 0.15706847 | M22: Fintual | Z22: 2Oy.kgzZS6ypW-BqTW5BBQ
A23: =ROW()-ROW($A$6)+1 -> 18 | B23: 46160 | C23: SCHD | D23: =IF(Tbla_Registros[[#This Row],[Ticker]]="","",_xlfn.XLOOKUP(Tbla_Registros[[#This Row],[Ticker]],$P$14:$P$19,$Q$14:$Q$19,Tbla_Registros[[#This Row],[Ticker]])) -> Schwab Dividend | E23: Compra | F23: 0.24452257 | G23: 31.86 | H23: 0 | I23: =Tbla_Registros[[#This Row],[Cantidad]] * Tbla_Registros[[#This Row],[Precio]] + Tbla_Registros[[#This Row],[Comisión]] -> 7.790489 | J23: =IF(C23="","",IFERROR((VLOOKUP(C23,Portafolio!$A$6:$C$8,3,FALSE)-G23)/G23,"")) -> 0.022912743 | K23: =IF(B23="","",TODAY()-B23) -> 17 | L23: =IFERROR((VLOOKUP(C23,Portafolio!$A$6:$C$8,3,FALSE)-G23)*F23,"") -> 0.17850147 | M23: Fintual | Z23: uLeeM6.mQ8KuvxDsE-8IEw
A24: =ROW()-ROW($A$6)+1 -> 19 | B24: 46174 | C24: SPYM | D24: =IF(Tbla_Registros[[#This Row],[Ticker]]="","",_xlfn.XLOOKUP(Tbla_Registros[[#This Row],[Ticker]],$P$14:$P$19,$Q$14:$Q$19,Tbla_Registros[[#This Row],[Ticker]])) -> SPDR S&P 500 | E24: Compra | F24: 0.29535 | G24: 89.02 | H24: 0 | I24: =Tbla_Registros[[#This Row],[Cantidad]] * Tbla_Registros[[#This Row],[Precio]] + Tbla_Registros[[#This Row],[Comisión]] -> 26.292057 | J24: =IF(C24="","",IFERROR((VLOOKUP(C24,Portafolio!$A$6:$C$8,3,FALSE)-G24)/G24,"")) -> 0.0010110088 | K24: =IF(B24="","",TODAY()-B24) -> 3 | L24: =IFERROR((VLOOKUP(C24,Portafolio!$A$6:$C$8,3,FALSE)-G24)*F24,"") -> 0.0265815 | M24: Webull | Z24: vLx1a6dVSWGpzmdoO3l9hw
A25: =ROW()-ROW($A$6)+1 -> 20 | B25: 46174 | C25: SCHD | D25: =IF(Tbla_Registros[[#This Row],[Ticker]]="","",_xlfn.XLOOKUP(Tbla_Registros[[#This Row],[Ticker]],$P$14:$P$19,$Q$14:$Q$19,Tbla_Registros[[#This Row],[Ticker]])) -> Schwab Dividend | E25: Compra | F25: 0.37736 | G25: 32.25 | H25: 0 | I25: =Tbla_Registros[[#This Row],[Cantidad]] * Tbla_Registros[[#This Row],[Precio]] + Tbla_Registros[[#This Row],[Comisión]] -> 12.16986 | J25: =IF(C25="","",IFERROR((VLOOKUP(C25,Portafolio!$A$6:$C$8,3,FALSE)-G25)/G25,"")) -> 0.010542636 | K25: =IF(B25="","",TODAY()-B25) -> 3 | L25: =IFERROR((VLOOKUP(C25,Portafolio!$A$6:$C$8,3,FALSE)-G25)*F25,"") -> 0.1283024 | M25: Webull | Z25: VxlaBDvBQgSNHbSf5RaFqQ
A26: =ROW()-ROW($A$6)+1 -> 21 | B26: 46174 | C26: SCHG | D26: =IF(Tbla_Registros[[#This Row],[Ticker]]="","",_xlfn.XLOOKUP(Tbla_Registros[[#This Row],[Ticker]],$P$14:$P$19,$Q$14:$Q$19,Tbla_Registros[[#This Row],[Ticker]])) -> Schwab Growth | E26: Compra | F26: 0.53259 | G26: 35.13 | H26: 0 | I26: =Tbla_Registros[[#This Row],[Cantidad]] * Tbla_Registros[[#This Row],[Precio]] + Tbla_Registros[[#This Row],[Comisión]] -> 18.709887 | J26: =IF(C26="","",IFERROR((VLOOKUP(C26,Portafolio!$A$6:$C$8,3,FALSE)-G26)/G26,"")) -> -0.0096783376 | K26: =IF(B26="","",TODAY()-B26) -> 3 | L26: =IFERROR((VLOOKUP(C26,Portafolio!$A$6:$C$8,3,FALSE)-G26)*F26,"") -> -0.1810806 | M26: Webull | Z26: kCOZwVm3QLWhkXZ6BnyW0Q

Sheet HHIReal
A1: 🏠 Inicio | B1: 📈 Portafolio | C1: 📊 Dashboard | D1: 📉 Historial | E1: 🗃️ Base de Datos | F1: 📊 Gráficos | G1: 🧩 HHI Real | AB1: 🔒 Row ID
M3: 📊 Índice HHI Real | P3: 📊 Resumen Diversificación | AB3: DOshh0y2Soe4LTCgyMkhQA
A4: 📊 Peso Actual en Portafolio | M4: Valor HHI: | N4: {=SUMPRODUCT((Tabla16[Peso Total])^2)*10000} -> 184.65694 | P4: Total Holdings: | Q4: =ROWS(Tablaholdings[])-1 -> 798 | AB4: VsGcEt.wQEqpAjQpZFfssg
A5: ETF | B5: Peso actual | M5: Estado: | N5: =IF(N4<1500,"✅ Muy Diversificado",IF(N4<2500,"⚠️ Moderadamente Concentrado","🔴 Altamente Concentrado")) -> ✅ Muy Diversificado | P5: Empresas Únicas: | Q5: =COUNTA(_xlfn.ANCHORARRAY($S$12))-IF(ISNUMBER(MATCH("-",_xlfn.ANCHORARRAY($S$12),0)),1,0) -> 629 | AB5: tMpouhoWRfqXApa.9ZyRZw
A6: SPYM | B6: =Portafolio!J6 -> 0.40155475 | M6: 📝 Interpretación: | P6: Top Holding: | Q6: =J12 -> NVDA | AB6: 6prN-FOBR3mKxH0ePBVlLA
A7: SCHD | B7: =Portafolio!J7 -> 0.30013645 | M7: HHI < 1500 = Diversificado | P7: Peso Top: | Q7: =K12 -> 0.071659471 | AB7: WYXT33amSPiPpJSY6Ubarw
A8: SCHG | B8: =Portafolio!J8 -> 0.29830879 | P8: Top 5 Conc.: | Q8: =SUM(K12:K16) -> 0.22967131 | AB8: rl5PtKeUSd6rEjRXdbm7EA
A10: 📊 Holdings Consolidados del Portafolio | J10: 🧩 Exposición Consolidada por Empresa | S10: 🔧 Motor de consolidación automática (no borrar) | AB10: 6iC7SV5fRMmCXHDyK5TT.Q
A11: Ticker | B11: Nombre Empresa | C11: Peso Interno ETF | D11: Peso Actual en ETF | E11: Peso Real en Portafolio | F11: ETF | J11: Ticker | K11: Peso Total | S11: Tickers únicos (auto) | AB11: 4ZTLwRKzQkq0353RfIazRw
A12: - | B12: SSI US GOV MONEY MARKET CLASS | C12: 0.049674 | D12: =C12/100 -> 0.00049674 | E12: =C12 * VLOOKUP(F12, $A$6:$B$8, 2, FALSE) -> 0.019946831 | F12: SPYM | J12: {=IFERROR(INDEX(_xlfn.ANCHORARRAY($S$12),ROW()-12+1),"")} -> NVDA | K12: =IF(Tabla16[[#This Row],[Ticker]]="",0,SUMIF(Tablaholdings[Ticker],Tabla16[[#This Row],[Ticker]],Tablaholdings[Peso Real en Portafolio])/100) -> 0.071659471 | S12: {=_xlfn.LET(_xlpm.u,_xlfn.UNIQUE(Tablaholdings[Ticker]),_xlpm.p,SUMIF(Tablaholdings[Ticker],_xlpm.u,Tablaholdings[Peso Real en Portafolio]),_xlfn.SORTBY(_xlpm.u,_xlpm.p,-1))} -> NVDA | AB12: oJIWczG3QOCebWnyP2171g
A13: A | B13: AGILENT TECHNOLOGIES INC | C13: 0.049979 | D13: =C13/100 -> 0.00049979 | E13: =C13 * VLOOKUP(F13, $A$6:$B$8, 2, FALSE) -> 0.020069305 | F13: SPYM | J13: {=IFERROR(INDEX(_xlfn.ANCHORARRAY($S$12),ROW()-12+1),"")} -> AAPL | K13: =IF(Tabla16[[#This Row],[Ticker]]="",0,SUMIF(Tablaholdings[Ticker],Tabla16[[#This Row],[Ticker]],Tablaholdings[Peso Real en Portafolio])/100) -> 0.055982166 | S13: AAPL | AB13: bT9O-XB5QIq3c6dXNvJzWQ
A14: AAL | B14: AMERICAN AIRLINES GROUP INC | C14: 0.0295915 | D14: =C14/100 -> 0.000295915 | E14: =C14 * VLOOKUP(F14, $A$6:$B$8, 2, FALSE) -> 0.0088274047 | F14: SCHG | J14: {=IFERROR(INDEX(_xlfn.ANCHORARRAY($S$12),ROW()-12+1),"")} -> MSFT | K14: =IF(Tabla16[[#This Row],[Ticker]]="",0,SUMIF(Tablaholdings[Ticker],Tabla16[[#This Row],[Ticker]],Tablaholdings[Peso Real en Portafolio])/100) -> 0.038632401 | S14: MSFT | AB14: LbiuTPWGTSSmjRuGt81YWw
A15: AAPL | B15: APPLE INC | C15: 9.5164716 | D15: =C15/100 -> 0.095164716 | E15: =C15 * VLOOKUP(F15, $A$6:$B$8, 2, FALSE) -> 2.8388472 | F15: SCHG | J15: {=IFERROR(INDEX(_xlfn.ANCHORARRAY($S$12),ROW()-12+1),"")} -> AMZN | K15: =IF(Tabla16[[#This Row],[Ticker]]="",0,SUMIF(Tablaholdings[Ticker],Tabla16[[#This Row],[Ticker]],Tablaholdings[Peso Real en Portafolio])/100) -> 0.033516097 | S15: AMZN | AB15: slbL9Vo8RuCnKNt1pALzbw
A16: AAPL | B16: APPLE INC | C16: 6.871714 | D16: =C16/100 -> 0.06871714 | E16: =C16 * VLOOKUP(F16, $A$6:$B$8, 2, FALSE) -> 2.7593694 | F16: SPYM | J16: {=IFERROR(INDEX(_xlfn.ANCHORARRAY($S$12),ROW()-12+1),"")} -> GOOGL | K16: =IF(Tabla16[[#This Row],[Ticker]]="",0,SUMIF(Tablaholdings[Ticker],Tabla16[[#This Row],[Ticker]],Tablaholdings[Peso Real en Portafolio])/100) -> 0.029881178 | S16: GOOGL | AB16: zDqPhJqiRVi1f8c0Oo4mYw
A17: ABBV | B17: ABBVIE INC | C17: 0.577109 | D17: =C17/100 -> 0.00577109 | E17: =C17 * VLOOKUP(F17, $A$6:$B$8, 2, FALSE) -> 0.23174086 | F17: SPYM | J17: {=IFERROR(INDEX(_xlfn.ANCHORARRAY($S$12),ROW()-12+1),"")} -> AVGO | K17: =IF(Tabla16[[#This Row],[Ticker]]="",0,SUMIF(Tablaholdings[Ticker],Tabla16[[#This Row],[Ticker]],Tablaholdings[Peso Real en Portafolio])/100) -> 0.025959696 | S17: AVGO | AB17: T03Pwj6KSQq7deMu7EAR0g
A18: ABNB | B18: AIRBNB INC CLASS A | C18: 0.20144367 | D18: =C18/100 -> 0.0020144367 | E18: =C18 * VLOOKUP(F18, $A$6:$B$8, 2, FALSE) -> 0.060092417 | F18: SCHG | J18: {=IFERROR(INDEX(_xlfn.ANCHORARRAY($S$12),ROW()-12+1),"")} -> GOOG | K18: =IF(Tabla16[[#This Row],[Ticker]]="",0,SUMIF(Tablaholdings[Ticker],Tabla16[[#This Row],[Ticker]],Tablaholdings[Peso Real en Portafolio])/100) -> 0.02377752 | S18: GOOG | AB18: 8VF3QW1nRvOc3govz0d0-A
A19: ABNB | B19: AIRBNB INC CLASS A | C19: 0.088107 | D19: =C19/100 -> 0.00088107 | E19: =C19 * VLOOKUP(F19, $A$6:$B$8, 2, FALSE) -> 0.035379785 | F19: SPYM | J19: {=IFERROR(INDEX(_xlfn.ANCHORARRAY($S$12),ROW()-12+1),"")} -> UNH | K19: =IF(Tabla16[[#This Row],[Ticker]]="",0,SUMIF(Tablaholdings[Ticker],Tabla16[[#This Row],[Ticker]],Tablaholdings[Peso Real en Portafolio])/100) -> 0.022487002 | S19: UNH | AB19: 0M7rd5ZESJ2oEJ7fMbXtiw
A20: ABT | B20: ABBOTT LABORATORIES | C20: 2.9997658 | D20: =C20/100 -> 0.029997658 | E20: =C20 * VLOOKUP(F20, $A$6:$B$8, 2, FALSE) -> 0.90033907 | F20: SCHD | J20: {=IFERROR(INDEX(_xlfn.ANCHORARRAY($S$12),ROW()-12+1),"")} -> TXN | K20: =IF(Tabla16[[#This Row],[Ticker]]="",0,SUMIF(Tablaholdings[Ticker],Tabla16[[#This Row],[Ticker]],Tablaholdings[Peso Real en Portafolio])/100) -> 0.020010487 | S20: TXN | AB20: udrZM1TEQQ6obeaVUHLzXA
A21: ABT | B21: ABBOTT LABORATORIES | C21: 0.228318 | D21: =C21/100 -> 0.00228318 | E21: =C21 * VLOOKUP(F21, $A$6:$B$8, 2, FALSE) -> 0.091682178 | F21: SPYM | J21: {=IFERROR(INDEX(_xlfn.ANCHORARRAY($S$12),ROW()-12+1),"")} -> TSLA | K21: =IF(Tabla16[[#This Row],[Ticker]]="",0,SUMIF(Tablaholdings[Ticker],Tabla16[[#This Row],[Ticker]],Tablaholdings[Peso Real en Portafolio])/100) -> 0.019897223 | S21: TSLA | AB21: 9IPkEUhqRkuAM1noGqsWSg
A22: ACGL | B22: ARCH CAPITAL GROUP LTD | C22: 0.052286 | D22: =C22/100 -> 0.00052286 | E22: =C22 * VLOOKUP(F22, $A$6:$B$8, 2, FALSE) -> 0.020995692 | F22: SPYM | J22: {=IFERROR(INDEX(_xlfn.ANCHORARRAY($S$12),ROW()-12+1),"")} -> META | K22: =IF(Tabla16[[#This Row],[Ticker]]="",0,SUMIF(Tablaholdings[Ticker],Tabla16[[#This Row],[Ticker]],Tablaholdings[Peso Real en Portafolio])/100) -> 0.018686842 | S22: META | AB22: jrohiqS9SRq-LLXqbDsI7g
A23: ACN | B23: ACCENTURE PLC CLASS A | C23: 2.594523 | D23: =C23/100 -> 0.02594523 | E23: =C23 * VLOOKUP(F23, $A$6:$B$8, 2, FALSE) -> 0.77871094 | F23: SCHD | J23: {=IFERROR(INDEX(_xlfn.ANCHORARRAY($S$12),ROW()-12+1),"")} -> QCOM | K23: =IF(Tabla16[[#This Row],[Ticker]]="",0,SUMIF(Tablaholdings[Ticker],Tabla16[[#This Row],[Ticker]],Tablaholdings[Peso Real en Portafolio])/100) -> 0.017906181 | S23: QCOM | AB23: zmFWr0SGRvW.ePmv-yBEEg
A24: ACN | B24: ACCENTURE PLC CL A | C24: 0.153864 | D24: =C24/100 -> 0.00153864 | E24: =C24 * VLOOKUP(F24, $A$6:$B$8, 2, FALSE) -> 0.061784821 | F24: SPYM | J24: {=IFERROR(INDEX(_xlfn.ANCHORARRAY($S$12),ROW()-12+1),"")} -> KO | K24: =IF(Tabla16[[#This Row],[Ticker]]="",0,SUMIF(Tablaholdings[Ticker],Tabla16[[#This Row],[Ticker]],Tablaholdings[Peso Real en Portafolio])/100) -> 0.014308299 | S24: KO | AB24: L-TD63kLQKKOXB6P4eG37g
... A641: RSG | B641: REPUBLIC SERVICES INC | C641: 0.064212 | D641: =C641/100 -> 0.00064212 | E641: =C641 * VLOOKUP(F641, $A$6:$B$8, 2, FALSE) -> 0.025784634 | F641: SPYM | J641: {=IFERROR(INDEX(_xlfn.ANCHORARRAY($S$12),ROW()-12+1),"")} -> PSKY | K641: =IF(Tabla16[[#This Row],[Ticker]]="",0,SUMIF(Tablaholdings[Ticker],Tabla16[[#This Row],[Ticker]],Tablaholdings[Peso Real en Portafolio])/100) -> 2.0346779e-05 | S641: PSKY | AB641: e7md5SWkQg-dmxeTCK88Tg
A642: RTX | B642: RTX CORP | C642: 0.374314 | D642: =C642/100 -> 0.00374314 | E642: =C642 * VLOOKUP(F642, $A$6:$B$8, 2, FALSE) -> 0.15030757 | F642: SPYM | AB642: rChgXzNNRKK5a.wk-U5cMQ
A643: RVTY | B643: REVVITY INC | C643: 0.016917 | D643: =C643/100 -> 0.00016917 | E643: =C643 * VLOOKUP(F643, $A$6:$B$8, 2, FALSE) -> 0.0067931018 | F643: SPYM | AB643: uK-ddh4rRa-MjFUI0472QQ
A644: SAIA | B644: SAIA INC | C644: 0.042371024 | D644: =C644/100 -> 0.00042371024 | E644: =C644 * VLOOKUP(F644, $A$6:$B$8, 2, FALSE) -> 0.012639649 | F644: SCHG | AB644: lMtWfJf7RKesZ4c3EAUnCQ
A645: SATS | B645: ECHOSTAR CORP A | C645: 0.02799 | D645: =C645/100 -> 0.0002799 | E645: =C645 * VLOOKUP(F645, $A$6:$B$8, 2, FALSE) -> 0.011239518 | F645: SPYM | AB645: jc-ckqgbSXmeXh5Ni13SGA
A646: SBAC | B646: SBA COMMUNICATIONS REIT CORP CLASS | C646: 0.075646144 | D646: =C646/100 -> 0.00075646144 | E646: =C646 * VLOOKUP(F646, $A$6:$B$8, 2, FALSE) -> 0.02256591 | F646: SCHG | AB646: NQPnyxvfTse7JyUJ8nLUcw
A647: SBAC | B647: SBA COMMUNICATIONS CORP | C647: 0.034676 | D647: =C647/100 -> 0.00034676 | E647: =C647 * VLOOKUP(F647, $A$6:$B$8, 2, FALSE) -> 0.013924313 | F647: SPYM | AB647: 5ufIbfqDSR2S-pSb8SL4Iw
A648: SBUX | B648: STARBUCKS CORPORATION | C648: 0.189092 | D648: =C648/100 -> 0.00189092 | E648: =C648 * VLOOKUP(F648, $A$6:$B$8, 2, FALSE) -> 0.075930791 | F648: SPYM | AB648: J7mdW5VGRTukTze3zfIsqw
A649: SCHW | B649: SCHWAB (CHARLES) CORP | C649: 0.238412 | D649: =C649/100 -> 0.00238412 | E649: =C649 * VLOOKUP(F649, $A$6:$B$8, 2, FALSE) -> 0.095735472 | F649: SPYM | AB649: DAojJ-agSES7tzcQvDTSuw
A650: SHW | B650: SHERWIN WILLIAMS | C650: 0.25154507 | D650: =C650/100 -> 0.0025154507 | E650: =C650 * VLOOKUP(F650, $A$6:$B$8, 2, FALSE) -> 0.075038106 | F650: SCHG | AB650: iFfGcRLcSdqfrwqjKkkJyw
A651: SHW | B651: SHERWIN WILLIAMS CO/THE | C651: 0.11063 | D651: =C651/100 -> 0.0011063 | E651: =C651 * VLOOKUP(F651, $A$6:$B$8, 2, FALSE) -> 0.044424002 | F651: SPYM | AB651: tLubGjbbSTqkvAjnnb.mlg
A652: SJM | B652: JM SMUCKER CO/THE | C652: 0.016755 | D652: =C652/100 -> 0.00016755 | E652: =C652 * VLOOKUP(F652, $A$6:$B$8, 2, FALSE) -> 0.0067280499 | F652: SPYM | AB652: 97irPktCSo6xJMHiQaw.xQ
A653: SLB | B653: SLB NV | C653: 2.1435902 | D653: =C653/100 -> 0.021435902 | E653: =C653 * VLOOKUP(F653, $A$6:$B$8, 2, FALSE) -> 0.64336954 | F653: SCHD | AB653: jkTb2R10TG2ZnR07RZtvLw
... A810: ZTS | B810: ZOETIS INC | C810: 0.049107 | D810: =C810/100 -> 0.00049107 | E810: =C810 * VLOOKUP(F810, $A$6:$B$8, 2, FALSE) -> 0.019719149 | F810: SPYM | AB810: KjWItfzGQ1uylc1ypYFNnA

Sheet Historial
A1: 🏠 Inicio | B1: 📈 Portafolio | C1: 📊 Dashboard | D1: 📉 Historial | E1: 🗃️ Base de Datos | F1: 📊 Gráficos | G1: 🧩 HHI Real | K1: 🔒 Row ID
A3: 📈 Historial de Valor del Portafolio | K3: ysrSGn2kQIGUwb2Wlz3DsQ
A4: Registro semanal/mensual del crecimiento de tu inversión | K4: ofGMgajyTImMDhvcT-aHFw
A6: 📅 Fecha | B6: 💰 Valor Portafolio | C6: 💵 Total Invertido | D6: 📈 Ganancia | E6: 📊 Rendimiento % | F6: 📉 S&P 500 YTD | G6: 🎯 Alpha | I6: 📝 Instrucciones | K6: Voh7nohbT02ST.s8gZojNw
A7: =TODAY() -> 46177 | B7: =Portafolio!E9 -> 555.31734 | C7: =Portafolio!F9 -> 510.67945 | D7: =B7-C7 -> 44.637891 | E7: =IF(C7>0,(B7-C7)/C7,0) -> 0.087408827 | F7: ='Base de Datos'!T8 -> 0.10820147 | G7: =E7-F7 -> -0.020792646 | I7: 1. La fila 5 muestra el valor ACTUAL (se actualiza solo) | K7: fmyDW4IOTwq6R2cTQzuf7A
D8: =IF(B8="","",B8-C8) | E8: =IF(C8="","",IF(C8>0,(B8-C8)/C8,0)) | G8: =IF(E8="","",E8-F8) | I8: 2. Para registrar historial, copia la fila 5 y pégala como VALORES | K8: FrAAYDPHRU2.7Foz16zOwA
D9: =IF(B9="","",B9-C9) | E9: =IF(C9="","",IF(C9>0,(B9-C9)/C9,0)) | G9: =IF(E9="","",E9-F9) | I9: 3. Registra semanalmente o mensualmente | K9: NRYFGZ0ISEuTUi3ZEO7UIA
D10: =IF(B10="","",B10-C10) | E10: =IF(C10="","",IF(C10>0,(B10-C10)/C10,0)) | G10: =IF(E10="","",E10-F10) | I10: 4. Las columnas D, E y G se calculan automáticamente | K10: m.vmXYFsTMuRGyPTuqiOtA
D11: =IF(B11="","",B11-C11) | E11: =IF(C11="","",IF(C11>0,(B11-C11)/C11,0)) | G11: =IF(E11="","",E11-F11) | I11: 5. Solo necesitas llenar: Fecha, Valor, Invertido y S&P 500 YTD | K11: VwTMD.Y0Q0e-4tbTjzQbfA
D12: =IF(B12="","",B12-C12) | E12: =IF(C12="","",IF(C12>0,(B12-C12)/C12,0)) | G12: =IF(E12="","",E12-F12)
D13: =IF(B13="","",B13-C13) | E13: =IF(C13="","",IF(C13>0,(B13-C13)/C13,0)) | G13: =IF(E13="","",E13-F13) | I13: 📊 Resumen del Historial | K13: FD5QmP1PTLegOUwkY6hixA
D14: =IF(B14="","",B14-C14) | E14: =IF(C14="","",IF(C14>0,(B14-C14)/C14,0)) | G14: =IF(E14="","",E14-F14) | I14: Valor Inicial: | J14: =B7 -> 555.31734 | K14: 8lSCfUl1TjOJmQmTGFV0og
D15: =IF(B15="","",B15-C15) | E15: =IF(C15="","",IF(C15>0,(B15-C15)/C15,0)) | G15: =IF(E15="","",E15-F15) | I15: Valor Actual: | J15: {=IFERROR(LOOKUP(2,1/(B7:B32<>""),B7:B32),"")} -> 555.31734 | K15: 8u60XyHqTFqnVcDWtUesPA
D16: =IF(B16="","",B16-C16) | E16: =IF(C16="","",IF(C16>0,(B16-C16)/C16,0)) | G16: =IF(E16="","",E16-F16) | I16: Crecimiento $: | J16: =J15-J14 -> 0 | K16: a-03DWVywTCeVOFeVKK1qJA
D17: =IF(B17="","",B17-C17) | E17: =IF(C17="","",IF(C17>0,(B17-C17)/C17,0)) | G17: =IF(E17="","",E17-F17) | I17: Crecimiento %: | J17: =IF(J14>0,(J15-J14)/J14,0) -> 0 | K17: 89lEIjYvSLq3PXQtt7qFZw
D18: =IF(B18="","",B18-C18) | E18: =IF(C18="","",IF(C18>0,(B18-C18)/C18,0)) | G18: =IF(E18="","",E18-F18) | I18: Registros: | J18: =COUNT(A7:A32) -> 1 | K18: NEoC.-ISQ5agB-P3YUm4yw
D19: =IF(B19="","",B19-C19) | E19: =IF(C19="","",IF(C19>0,(B19-C19)/C19,0)) | G19: =IF(E19="","",E19-F19) | I19: Primer Registro: | J19: =IF(COUNT(A7:A32)>0,MIN(A7:A32),"") -> 46177 | K19: RIJyCRg5SmOqO.XjHAvrcg
D20: =IF(B20="","",B20-C20) | E20: =IF(C20="","",IF(C20>0,(B20-C20)/C20,0)) | G20: =IF(E20="","",E20-F20) | I20: Último Registro: | J20: {=IFERROR(LOOKUP(2,1/(B7:B32<>""),A7:A32),"")} -> 46177 | K20: B88ynpEORpii-.jYPHbxKQ
D21: =IF(B21="","",B21-C21) | E21: =IF(C21="","",IF(C21>0,(B21-C21)/C21,0)) | G21: =IF(E21="","",E21-F21)
D22: =IF(B22="","",B22-C22) | E22: =IF(C22="","",IF(C22>0,(B22-C22)/C22,0)) | G22: =IF(E22="","",E22-F22)
D23: =IF(B23="","",B23-C23) | E23: =IF(C23="","",IF(C23>0,(B23-C23)/C23,0)) | G23: =IF(E23="","",E23-F23)
D24: =IF(B24="","",B24-C24) | E24: =IF(C24="","",IF(C24>0,(B24-C24)/C24,0)) | G24: =IF(E24="","",E24-F24)
D25: =IF(B25="","",B25-C25) | E25: =IF(C25="","",IF(C25>0,(B25-C25)/C25,0)) | G25: =IF(E25="","",E25-F25)
D26: =IF(B26="","",B26-C26) | E26: =IF(C26="","",IF(C26>0,(B26-C26)/C26,0)) | G26: =IF(E26="","",E26-F26)
D27: =IF(B27="","",B27-C27) | E27: =IF(C27="","",IF(C27>0,(B27-C27)/C27,0)) | G27: =IF(E27="","",E27-F27)
D28: =IF(B28="","",B28-C28) | E28: =IF(C28="","",IF(C28>0,(B28-C28)/C28,0)) | G28: =IF(E28="","",E28-F28)
D29: =IF(B29="","",B29-C29) | E29: =IF(C29="","",IF(C29>0,(B29-C29)/C29,0)) | G29: =IF(E29="","",E29-F29)
D30: =IF(B30="","",B30-C30) | E30: =IF(C30="","",IF(C30>0,(B30-C30)/C30,0)) | G30: =IF(E30="","",E30-F30)
D31: =IF(B31="","",B31-C31) | E31: =IF(C31="","",IF(C31>0,(B31-C31)/C31,0)) | G31: =IF(E31="","",E31-F31)
D32: =IF(B32="","",B32-C32) | E32: =IF(C32="","",IF(C32>0,(B32-C32)/C32,0)) | G32: =IF(E32="","",E32-F32)
